{
  "title": "Кредиты",
  "slug": "credits",
  "description": "Акционерное общество «Российский Сельскохозяйственный банк»* — один из крупнейших банков в России. Созданный в 2000 году в целях развития национальной кредитно-финансовой системы.",
  "keywords": ["кредит", "акция"],
  "robots": ["index", "follow"],
  "og": {
    "type": "article",
    "url": "https://foo.com/bar/baz"
  },
  "date": "2022-04-08",
  "style": ["bg-secondary-light"],
  "likeControl": true,
  "slots": {
    "header": {
      "style": ["mb-5", "shadow-[0_8px_32px_0px_#00000014]"],
      "blocks": [
        {
          "type": "Header",
          "content": {
            "defaultLocation": "Москва"
          }
        }
      ]
    }
  },
  "blocks": [
    {
      "type": "ProductGallery",
      "style": ["col-span-12"],
      "content": {
        "slides": [
          {
            "nav": {
              "title": "Деньги на любые цели",
              "desc": "Ставка от 12,5% годовых на срок до 5 лет"
            },
            "productBlock": {
              "title": "Ставка от 12,5% годовых на срок до 5 лет!»",
              "items": [
                "Потребительский кредит по специальной процентной ставке",
                "Получите деньги без залога и поручительства",
                "Кредитный лимит до 5 млн рублей"
              ],
              "buttons": [
                {
                  "href": "https://rshb.ru",
                  "text": "Подробнее",
                  "target": "_blank",
                  "version": "primary"
                }
              ],
              "image": {
                "src": "money-1.png",
                "title": "деньги",
                "format": "webp",
                "alt": "Кредит наличными",
                "size": {
                  "width": 280,
                  "height": 280
                }
              }
            }
          },
          {
            "nav": {
              "title": "Для людей в возрасте",
              "desc": "Ставка от 12,5% годовых на срок до 3 лет"
            },
            "productBlock": {
              "title": "Ставка от 12,5% годовых на срок до 3 лет!»",
              "items": [
                "Потребительский кредит по специальной процентной ставке",
                "Получите деньги без залога и поручительства",
                "Кредитный лимит до 5 млн рублей"
              ],
              "buttons": [
                {
                  "href": "https://rshb.ru",
                  "text": "Подробнее",
                  "target": "_blank",
                  "version": "primary"
                }
              ],
              "image": {
                "src": "money-2.png",
                "title": "Деньги",
                "format": "webp",
                "alt": "Кредит наличными",
                "size": {
                  "width": 280,
                  "height": 280
                }
              }
            }
          },
          {
            "nav": {
              "title": "Выгодно покупать",
              "desc": "Дополнительные бонусные баллы за покупки"
            },
            "productBlock": {
              "title": "Дополнительные бонусные баллы за покупки!»",
              "buttons": [
                {
                  "href": "https://rshb.ru",
                  "text": "Подробнее",
                  "target": "_blank",
                  "version": "primary"
                }
              ],
              "image": {
                "src": "credit-card-1.png",
                "title": "Кредитка",
                "format": "webp",
                "alt": "Кредит наличными",
                "size": {
                  "width": 280,
                  "height": 280
                }
              }
            }
          },
          {
            "nav": {
              "title": "Карты Unionpay",
              "desc": "Кэшбэк до 20% у партнеров"
            },
            "productBlock": {
              "title": "Карты Unionpay»",
              "items": [
                "Потребительский кредит по специальной процентной ставке",
                "Получите деньги без залога и поручительства",
                "Кредитный лимит до 5 млн рублей"
              ],
              "buttons": [
                {
                  "href": "https://rshb.ru",
                  "text": "Подробнее",
                  "target": "_blank",
                  "version": "primary"
                }
              ],
              "image": {
                "src": "credit-card-1.png",
                "title": "Кредитка",
                "format": "webp",
                "alt": "Кредит наличными",
                "size": {
                  "width": 280,
                  "height": 280
                }
              }
            }
          }
        ]
      }
    },
    {
      "type": "Unknown",
      "style": ["col-span-12"],
      "content": {
        "title": "Какой то новый блок"
      }
    },
    {
      "type": "ProductBlock",
      "style": ["col-span-12"],
      "content": {
        "title": "Потребительский кредит наличными",
        "description": "Кредит наличными без залога и поручительства. Потребительский кредит на любые цели. Нужен только паспорт.",
        "breadcrumbs": [
          {
            "text": "Главная",
            "href": "/"
          },
          {
            "text": "Кредитные карты",
            "href": "/credit"
          },
          {
            "text": "Кредитная карта Своя Union Pay"
          }
        ],
        "benefits": [
          {
            "label": "До 5 млн ₽",
            "description": "Кредитный лимит",
            "icon": "EmptyWalletIcon"
          },
          {
            "label": "От 16,9%",
            "description": "Ставка по кредиту",
            "icon": "PercentageSquareIcon"
          },
          {
            "label": "До 5 лет",
            "description": "Срок кредитования",
            "icon": "CalendarIcon"
          }
        ],
        "buttons": [
          {
            "href": "https://rshb.ru",
            "text": "Оформить карту",
            "target": "_blank",
            "version": "primary"
          },
          {
            "href": "https://rshb.ru",
            "text": "Подробнее",
            "target": "_blank",
            "version": "secondary"
          }
        ],
        "image": {
          "src": "money-1.png",
          "alt": "Кредиты в РСХБ",
          "format": "webp",
          "size": {
            "width": 280,
            "height": 280
          }
        }
      }
    },
    {
      "type": "StepsBlock",
      "style": ["col-span-12"],
      "content": {
        "title": "Рассчитайте условия на онлайн-калькуляторе и оставьте заявку на потребительский кредит",
        "steps": [
          {
            "label": "Заявка на кредит",
            "description": "Оставьте онлайн-заявку на потребительский кредит"
          },
          {
            "label": "В случае одобрения",
            "description": "Менеджер свяжется с вами и согласует встречу"
          },
          {
            "label": "Получение наличных",
            "description": "Получите наличные в отделении банка"
          }
        ]
      }
    },
    {
      "type": "TextBlock",
      "style": ["col-span-12"],
      "content": {
        "title": "Все карты Россельхозбанка работают",
        "description": "Если не планируете поездку за границу, продолжайте пользоваться картой Своя. Для поездок за границу можно заказать карту 'Кредитная карта Своя Union Pay' на сайте и в приложении Россельхозбанка",
        "blockVersion": "primary",
        "iconVersion": "small"
      }
    },
    {
      "type": "Headline",
      "style": ["col-span-12"],
      "content": {
        "title": "Своя кредитная карта",
        "description": "Карта работает в 180 странах мира. Бесплатное снятие наличных в любых банкоматах.",
        "align": "center",
        "bgColor": "transparent"
      }
    },
    {
      "type": "LinkDocs",
      "style": ["col-span-12"],
      "content": {
        "title": "Дополнительные документы",
        "subtitle": "Ответы на часто задаваемые вопросы",
        "icon": "DocIcon",
        "documents": [
          {
            "text": "target self",
            "href": "/abc1/cooldoc.doc",
            "target": "_self"
          },
          {
            "text": "target blank",
            "href": "/abc2/wtf.rtf",
            "target": "_blank"
          },
          {
            "text": "GlassIcon",
            "href": "/abc3/map.jpeg"
          },
          {
            "text": "no icon",
            "href": "/abc4"
          },
          {
            "text": "документ 5",
            "href": "/abc5"
          },
          {
            "text": "документ 6",
            "href": "/abc6/abc.pdf"
          },
          {
            "text": "Text text text",
            "href": "/abc7/yolo.png"
          },
          {
            "text": "Some more generic text, and even more, more text, and more generic text, and even more, more text, and even more",
            "href": "/abc8/archive.zip",
            "fileSize": "2.3МБ"
          },
          {
            "text": "И ещё немного текста",
            "href": "/abc9/rarniw.rar",
            "fileSize": "666МБ"
          },
          {
            "text": "Форматируем, сортируем, смотрим как отображается...",
            "href": "/abc10/",
            "fileSize": "65ГБ"
          }
        ]
      }
    },
    {
      "type": "Footer",
      "style": ["col-span-12"],
      "content": {
        "topItems": [
          {
            "href": "https://rshb.ru/",
            "text": "Частным клиентам",
            "target": "_blank",
            "items": [
              {
                "href": "https://rshb.ru/",
                "text": "Кредитные карты"
              },
              {
                "href": "https://rshb.ru/",
                "text": "Дебетовые карты"
              },
              {
                "href": "https://rshb.ru/",
                "text": "Кредиты"
              },
              {
                "href": "https://rshb.ru/",
                "text": "Ипотека"
              },
              {
                "href": "https://rshb.ru/",
                "text": "Вклады и сбережения"
              },
              {
                "href": "https://rshb.ru/",
                "text": "Инвестиции"
              },
              {
                "href": "https://rshb.ru/",
                "text": "Страхование"
              },
              {
                "href": "https://rshb.ru/",
                "text": "Премиальным клиентам"
              },
              {
                "href": "https://rshb.ru/",
                "text": "Биометрическая регистрация"
              },
              {
                "href": "https://rshb.ru/",
                "text": "Перевод денег"
              },
              {
                "href": "https://rshb.ru/",
                "text": "Обмен денег"
              },
              {
                "href": "https://rshb.ru/",
                "text": "Акции"
              },
              {
                "href": "https://rshb.ru/",
                "text": "Тарифы"
              },
              {
                "href": "https://rshb.ru/",
                "text": "Архивная информация"
              }
            ]
          },
          {
            "href": "https://rshb.ru/",
            "text": "Бизнес клиентам",
            "target": "_blank",
            "items": [
              {
                "href": "https://rshb.ru/",
                "text": "РКО"
              },
              {
                "href": "https://rshb.ru/",
                "text": "Кредиты"
              },
              {
                "href": "https://rshb.ru/",
                "text": "Депозиты"
              },
              {
                "href": "https://rshb.ru/",
                "text": "Эквайринг"
              },
              {
                "href": "https://rshb.ru/",
                "text": "Банковские карты"
              },
              {
                "href": "https://rshb.ru/",
                "text": "ВЭД"
              },
              {
                "href": "https://rshb.ru/",
                "text": "Инвестиции"
              },
              {
                "href": "https://rshb.ru/",
                "text": "Обмен валюты"
              },
              {
                "href": "https://rshb.ru/",
                "text": "Страхование"
              },
              {
                "href": "https://rshb.ru/",
                "text": "Партнёрские программы"
              },
              {
                "href": "https://rshb.ru/",
                "text": "Онлайн-сервисы"
              },
              {
                "href": "https://rshb.ru/",
                "text": "Акции"
              },
              {
                "href": "https://rshb.ru/",
                "text": "Тарифы"
              },
              {
                "href": "https://rshb.ru/",
                "text": "Архивная информация"
              }
            ]
          }
        ],
        "contacts": [
          {
            "text": "+7 (495) 787-7-787",
            "description": "Для звонков из-за границы",
            "type": "tel"
          },
          {
            "text": "example@example.com",
            "description": "Для писем",
            "type": "email"
          },
          {
            "text": "7787",
            "description": "Абонентам МТС, Мегафон, Билайн и Tele2",
            "type": "tel"
          }
        ],
        "documents": [
          {
            "text": "Информация о процентных ставках по договорам банковского вклада с физическими лицами",
            "href": "https://rshb.ru/",
            "target": "_blank"
          },
          {
            "text": "Раскрытие информации профессиональным участником рынка ценных бумаг",
            "href": "https://rshb.ru/",
            "target": "_blank"
          },
          {
            "text": "Раскрытие информации",
            "href": "https://rshb.ru/",
            "target": "_blank"
          },
          {
            "text": "Удостоверяющий центр",
            "href": "https://rshb.ru/",
            "target": "_blank"
          },
          {
            "text": "Финансовая культура",
            "href": "https://rshb.ru/",
            "target": "_blank"
          }
        ],
        "socialMedia": [
          { "href": "https://vk.com" },
          { "href": "https://ok.ru" },
          { "href": "https://t.me" }
        ]
      }
    }
  ]
}
